harmonyos/__init__.py
harmonyos-0.0.1.dist-info/LICENSE
harmonyos-0.0.1.dist-info/METADATA
harmonyos-0.0.1.dist-info/WHEEL
harmonyos-0.0.1.dist-info/top_level.txt
harmonyos-0.0.1.dist-info/RECORD
