Metadata-Version: 2.1
Name: harmonyos
Version: 0.0.1
Summary: HarmonyOS
Home-page: https://gitee.com/testpage/harmonyos
Author: ituser
Author-email: ituser@126.com
License: UNKNOWN
Project-URL: Bug Tracker, https://gitee.com/testpage/harmonyos/issues
Platform: UNKNOWN
Classifier: Programming Language :: Python :: 3
Classifier: License :: OSI Approved :: GNU General Public License v2 or later (GPLv2+)
Classifier: Operating System :: OS Independent
Requires-Python: >=3.5
License-File: LICENSE
